pytoshop/enums.py
pytoshop/image_data.py
pytoshop/packbits.cpython-310-darwin.so
pytoshop/blending_range.py
pytoshop/util.py
pytoshop/codecs.py
pytoshop/__init__.py
pytoshop/docs.py
pytoshop/core.py
pytoshop/tagged_block.py
pytoshop/color_mode.py
pytoshop/layers.py
pytoshop/image_resources.py
pytoshop/path.py
pytoshop/packbits.pyi
pytoshop/user/__init__.py
pytoshop/user/nested_layers.py
pytoshop_whl-0.1.4.dist-info/RECORD
pytoshop_whl-0.1.4.dist-info/WHEEL
pytoshop_whl-0.1.4.dist-info/METADATA
