Metadata-Version: 2.1
Name: pytoshop-whl
Version: 0.1.4
Summary: Add your description here
Requires-Python: >=3.10
Requires-Dist: numpy>=1.11
Requires-Dist: six>=1.17.0
